cogent_base/__init__.py
cogent_base/completion/__init__.py
cogent_base/completion/base_completion.py
cogent_base/completion/cogent_completion.py
cogent_base/completion/litellm_completion.py
cogent_base/completion/ollama_completion.py
cogent_base/config/__init__.py
cogent_base/config/base.py
cogent_base/config/consts.py
cogent_base/config/core.py
cogent_base/config/registry.py
cogent_base/config/utils.py
cogent_base/embedding/__init__.py
cogent_base/embedding/base_embedding.py
cogent_base/embedding/cogent_embedding.py
cogent_base/embedding/litellm_embedding.py
cogent_base/embedding/ollama_embedding.py
cogent_base/logger.py
cogent_base/models/chat.py
cogent_base/models/chunk.py
cogent_base/models/completion.py
cogent_base/models/video.py
cogent_base/ollama/__init__.py
cogent_base/reranker/__init__.py
cogent_base/reranker/base_reranker.py
cogent_base/reranker/cogent_reranker.py
cogent_base/reranker/flag_reranker.py
cogent_base/reranker/litellm_reranker.py
cogent_base/reranker/ollama_reranker.py
cogent_base/rootdir.py
cogent_base/sensory/chunker/base_chunker.py
cogent_base/sensory/chunker/contextual_chunker.py
cogent_base/sensory/chunker/standard_chunker.py
cogent_base/sensory/parser/base_parser.py
cogent_base/sensory/parser/cogent_parser.py
cogent_base/sensory/parser/video_parser.py
cogent_base/smart_frame/__init__.py
cogent_base/smart_frame/base_pandasai.py
cogent_base/smart_frame/cogent_pandasai.py
cogent_base/smart_frame/dashscope_pandasai.py
cogent_base/smart_voice/__init__.py
cogent_base/smart_voice/base_smart_voice.py
cogent_base/smart_voice/cogent_smart_voice.py
cogent_base/vector_store/__init__.py
cogent_base/vector_store/base_vector_store.py
cogent_base/vector_store/cogent_vector_store.py
cogent_base/vector_store/models.py
cogent_base/vector_store/pgvector_vector_store.py
cogent_base/vector_store/weaviate_vector_store.py
cogent_base/version.py
cogent_base-0.1.17.dist-info/LICENSE
cogent_base-0.1.17.dist-info/METADATA
cogent_base-0.1.17.dist-info/WHEEL
cogent_base-0.1.17.dist-info/RECORD
