Metadata-Version: 2.3
Name: cogent-base
Version: 0.1.17
Summary: Base and shared modules for cogents
Author: xmingc
Author-email: chenxm35@gmail.com
Requires-Python: >=3.10,<3.12
Classifier: Programming Language :: Python :: 3
Classifier: Programming Language :: Python :: 3.10
Classifier: Programming Language :: Python :: 3.11
Requires-Dist: filetype (>=1.2.0)
Requires-Dist: instructor (>=1.9.0)
Requires-Dist: litellm (>=1.74.0)
Requires-Dist: ollama (>=0.5.0)
Requires-Dist: opencv-python (>=4.9.0)
Requires-Dist: pydantic (>=2.8.0)
Requires-Dist: python-dotenv (>=1.0.0)
Requires-Dist: unstructured (>=0.18.0)
